{
  "updated": "2026-03-11T21:49:08.380Z",
  "count": 20,
  "items": [
    {
      "title": "عاجل | الحرس الثوري: وجهنا ضربات مهلكة الليلة على ٥٠ هدفا في الأراضي المحتلة ضمن الموجة ٤٠ من عملية الوعد الصادق ٤",
      "source": "telegram",
      "sourceName": "الجزيرة عاجل",
      "handle": "ajanews",
      "pubDate": "2026-03-11T21:47:40.000Z",
      "link": "https://t.me/AjaNews/466327",
      "mediaUrl": null,
      "customAvatar": "public/logos/aljazeera.png",
      "customName": "الجزيرة عاجل"
    },
    {
      "title": "عاجل | القناة 12 الإسرائيلية: شركة القطارات بلغت عن تشويش بلوحات الإعلانات في بعض محطات القطار وأوقفت تشغيلها مؤقتا",
      "source": "telegram",
      "sourceName": "الجزيرة عاجل",
      "handle": "ajanews",
      "pubDate": "2026-03-11T21:46:05.000Z",
      "link": "https://t.me/AjaNews/466326",
      "mediaUrl": null,
      "customAvatar": "public/logos/aljazeera.png",
      "customName": "الجزيرة عاجل"
    },
    {
      "title": "عاجل | مراسل #الجزيرة عن وزارة الصحة: 8 شهداء و3 مصابين في الغارة الإسرائيلية على بلدة شعث في البقاع شرقي #لبنان",
      "source": "telegram",
      "sourceName": "الجزيرة عاجل",
      "handle": "ajanews",
      "pubDate": "2026-03-11T21:44:35.000Z",
      "link": "https://t.me/AjaNews/466325",
      "mediaUrl": null,
      "customAvatar": "public/logos/aljazeera.png",
      "customName": "الجزيرة عاجل"
    },
    {
      "title": "عاجل | مسؤول التنسيق بين قسد والقوات الأمريكية: القوات الأمريكية أعادت قطعا عسكرية لقاعدة قسرك بريف الحسكة",
      "source": "telegram",
      "sourceName": "الجزيرة عاجل",
      "handle": "ajanews",
      "pubDate": "2026-03-11T21:44:10.000Z",
      "link": "https://t.me/AjaNews/466324",
      "mediaUrl": null,
      "customAvatar": "public/logos/aljazeera.png",
      "customName": "الجزيرة عاجل"
    },
    {
      "title": "عاجل | رويترز عن مصادر أمنية: سقوط طائرتين مسيرتين في حقل مجنون النفطي بجنوب #العراق ولا إصابات",
      "source": "telegram",
      "sourceName": "الجزيرة عاجل",
      "handle": "ajanews",
      "pubDate": "2026-03-11T21:43:40.000Z",
      "link": "https://t.me/AjaNews/466323",
      "mediaUrl": null,
      "customAvatar": "public/logos/aljazeera.png",
      "customName": "الجزيرة عاجل"
    },
    {
      "title": "عاجل | مراسل #الجزيرة: 8 شهداء و3 مصابين في الغارة الإسرائيلية على بلدة شعث في البقاع شرقي #لبنان",
      "source": "telegram",
      "sourceName": "الجزيرة عاجل",
      "handle": "ajanews",
      "pubDate": "2026-03-11T21:41:39.000Z",
      "link": "https://t.me/AjaNews/466322",
      "mediaUrl": null,
      "customAvatar": "public/logos/aljazeera.png",
      "customName": "الجزيرة عاجل"
    },
    {
      "title": "عاجل | وزارة الصحة اللبنانية: 17 مصابا في الغارات الإسرائيلية على الضاحية الجنوبية لبيروت",
      "source": "telegram",
      "sourceName": "الجزيرة عاجل",
      "handle": "ajanews",
      "pubDate": "2026-03-11T21:41:09.000Z",
      "link": "https://t.me/AjaNews/466321",
      "mediaUrl": null,
      "customAvatar": "public/logos/aljazeera.png",
      "customName": "الجزيرة عاجل"
    },
    {
      "title": "عاجل | القيادة المركزية الأمريكية: هدفنا العسكري القضاء على قدرة #إيران على بسط نفوذها ضد أمريكا وجيرانها",
      "source": "telegram",
      "sourceName": "الجزيرة عاجل",
      "handle": "ajanews",
      "pubDate": "2026-03-11T21:40:45.000Z",
      "link": "https://t.me/AjaNews/466320",
      "mediaUrl": null,
      "customAvatar": "public/logos/aljazeera.png",
      "customName": "الجزيرة عاجل"
    },
    {
      "title": "عاجل | وزارة الصحة اللبنانية: 6 شهداء و15 مصابا في غارات إسرائيلية على دير انطار والبرج الشمالي جنوبي البلاد",
      "source": "telegram",
      "sourceName": "الجزيرة عاجل",
      "handle": "ajanews",
      "pubDate": "2026-03-11T21:40:34.000Z",
      "link": "https://t.me/AjaNews/466319",
      "mediaUrl": null,
      "customAvatar": "public/logos/aljazeera.png",
      "customName": "الجزيرة عاجل"
    },
    {
      "title": "عاجل | القناة 12 الإسرائيلية: دوي انفجارات وسط إسرائيل دون إنذارات جراء سقوط صواريخ من #لبنان في منطقة مفتوحة",
      "source": "telegram",
      "sourceName": "الجزيرة عاجل",
      "handle": "ajanews",
      "pubDate": "2026-03-11T21:39:41.000Z",
      "link": "https://t.me/AjaNews/466318",
      "mediaUrl": null,
      "customAvatar": "public/logos/aljazeera.png",
      "customName": "الجزيرة عاجل"
    },
    {
      "title": "عاجل | الحرس الثوري الإيراني: أطلقنا صاروخ خرمشهر متعدد الرؤوس باتجاه الأراضي المحتلة",
      "source": "telegram",
      "sourceName": "الجزيرة عاجل",
      "handle": "ajanews",
      "pubDate": "2026-03-11T21:35:09.000Z",
      "link": "https://t.me/AjaNews/466317",
      "mediaUrl": null,
      "customAvatar": "public/logos/aljazeera.png",
      "customName": "الجزيرة عاجل"
    },
    {
      "title": "عاجل | ترمب: عملية الغضب الملحمي اسم رائع وقد فزنا وكسبنا الرهان وانتهى الأمر خلال الساعة الأولى",
      "source": "telegram",
      "sourceName": "الجزيرة عاجل",
      "handle": "ajanews",
      "pubDate": "2026-03-11T21:31:38.000Z",
      "link": "https://t.me/AjaNews/466316",
      "mediaUrl": null,
      "customAvatar": "public/logos/aljazeera.png",
      "customName": "الجزيرة عاجل"
    },
    {
      "title": "عاجل | حزب الله: استهدفنا مستوطنة شلومي بسرب من المسيرات الانقضاضية",
      "source": "telegram",
      "sourceName": "الجزيرة عاجل",
      "handle": "ajanews",
      "pubDate": "2026-03-11T21:30:38.000Z",
      "link": "https://t.me/AjaNews/466315",
      "mediaUrl": null,
      "customAvatar": "public/logos/aljazeera.png",
      "customName": "الجزيرة عاجل"
    },
    {
      "title": "عاجل | وزارة الدفاع الكويتية: الدفاعات الجوية تصدت لعدد من الصواريخ الباليستية اخترقت الأجواء باتجاه جنوب البلاد",
      "source": "telegram",
      "sourceName": "الجزيرة عاجل",
      "handle": "ajanews",
      "pubDate": "2026-03-11T21:27:38.000Z",
      "link": "https://t.me/AjaNews/466314",
      "mediaUrl": null,
      "customAvatar": "public/logos/aljazeera.png",
      "customName": "الجزيرة عاجل"
    },
    {
      "title": "عاجل | وزارة الدفاع #السعودية: اعتراض وتدمير مسيرة بالمنطقة الشرقية",
      "source": "telegram",
      "sourceName": "الجزيرة عاجل",
      "handle": "ajanews",
      "pubDate": "2026-03-11T21:23:07.000Z",
      "link": "https://t.me/AjaNews/466313",
      "mediaUrl": null,
      "customAvatar": "public/logos/aljazeera.png",
      "customName": "الجزيرة عاجل"
    },
    {
      "title": "عاجل | حزب الله: استهدفنا قاعدة ستيلا ماريس بسرب من المسيرات الانقضاضية",
      "source": "telegram",
      "sourceName": "الجزيرة عاجل",
      "handle": "ajanews",
      "pubDate": "2026-03-11T21:22:37.000Z",
      "link": "https://t.me/AjaNews/466312",
      "mediaUrl": null,
      "customAvatar": "public/logos/aljazeera.png",
      "customName": "الجزيرة عاجل"
    },
    {
      "title": "عاجل | الخارجية #السعودية: نرحب بقرار مجلس الأمن الذي يدين الهجمات الشنيعة لإيران على أراضي الدول الخليجية والأردن",
      "source": "telegram",
      "sourceName": "الجزيرة عاجل",
      "handle": "ajanews",
      "pubDate": "2026-03-11T21:22:07.000Z",
      "link": "https://t.me/AjaNews/466311",
      "mediaUrl": null,
      "customAvatar": "public/logos/aljazeera.png",
      "customName": "الجزيرة عاجل"
    },
    {
      "title": "عاجل | ترمب: أسعار النفط بدأت في التراجع وستواصل التراجع ولن نتوقف حتى إنجاز المهمة بالكامل وسيكون ذلك سريعا",
      "source": "telegram",
      "sourceName": "الجزيرة عاجل",
      "handle": "ajanews",
      "pubDate": "2026-03-11T21:18:07.000Z",
      "link": "https://t.me/AjaNews/466310",
      "mediaUrl": null,
      "customAvatar": "public/logos/aljazeera.png",
      "customName": "الجزيرة عاجل"
    },
    {
      "title": "عاجل | ترمب: لن نتوقف حتى ننهي مهمتنا في #إيران",
      "source": "telegram",
      "sourceName": "الجزيرة عاجل",
      "handle": "ajanews",
      "pubDate": "2026-03-11T21:14:06.000Z",
      "link": "https://t.me/AjaNews/466309",
      "mediaUrl": null,
      "customAvatar": "public/logos/aljazeera.png",
      "customName": "الجزيرة عاجل"
    },
    {
      "title": "عاجل | ترمب: وكالة الطاقة الدولية وافقت على تنسيق سحب قياسي لـ400 مليون برميل نفط من الاحتياطيات العالمية",
      "source": "telegram",
      "sourceName": "الجزيرة عاجل",
      "handle": "ajanews",
      "pubDate": "2026-03-11T21:13:08.000Z",
      "link": "https://t.me/AjaNews/466308",
      "mediaUrl": null,
      "customAvatar": "public/logos/aljazeera.png",
      "customName": "الجزيرة عاجل"
    }
  ]
}